decorana/__init__.py
decorana/decorana.py
twinspan/__init__.py
twinspan/twinspan.py
utils/__init__.py
utils/make_cepnames.py
utils/write_cep.py
cornpy-0.1.0.dist-info/LICENSE
cornpy-0.1.0.dist-info/METADATA
cornpy-0.1.0.dist-info/WHEEL
cornpy-0.1.0.dist-info/top_level.txt
cornpy-0.1.0.dist-info/RECORD
