Metadata-Version: 2.1
Name: cornpy
Version: 0.1.0
Summary: Cornell Ecology Programs in Python
Home-page: https://github.com/maurobio/cornpy
Author: Mauro Cavalcanti
Author-email: maurobio@gmail.com
License: UNKNOWN
Keywords: ordination,classification,ecology,multivariate data analysis
Platform: UNKNOWN
Classifier: Programming Language :: Python :: 3
Classifier: License :: OSI Approved :: GNU General Public License (GPL)
Classifier: Operating System :: OS Independent
Classifier: Intended Audience :: Science/Research
Classifier: Topic :: Scientific/Engineering :: Bio-Informatics
Requires-Dist: numpy (>=1.7)
Requires-Dist: scipy (>=0.14)
Requires-Dist: matplotlib (>=1.3.1)
Requires-Dist: pandas (>=0.13)
